media_processing_lib/__init__.py
media_processing_lib/utils.py
media_processing_lib/audio/__init__.py
media_processing_lib/audio/audio_reader.py
media_processing_lib/audio/audio_writer.py
media_processing_lib/audio/mpl_audio.py
media_processing_lib/audio/resample.py
media_processing_lib/audio/melspectrogram/__init__.py
media_processing_lib/audio/melspectrogram/melspectrogram.py
media_processing_lib/image/__init__.py
media_processing_lib/image/image_reader.py
media_processing_lib/image/image_writer.py
media_processing_lib/image/utils.py
media_processing_lib/image/resize/__init__.py
media_processing_lib/image/resize/resize.py
media_processing_lib/image/resize/resize_black_bars.py
media_processing_lib/image/resize/resize_stretch.py
media_processing_lib/video/__init__.py
media_processing_lib/video/video_reader.py
media_processing_lib/video/video_writer.py
media_processing_lib/video/libs/__init__.py
media_processing_lib/video/libs/imageio/__init__.py
media_processing_lib/video/libs/imageio/reader.py
media_processing_lib/video/libs/imageio/writer.py
media_processing_lib/video/libs/opencv/__init__.py
media_processing_lib/video/libs/opencv/reader.py
media_processing_lib/video/libs/opencv/writer.py
media_processing_lib/video/libs/pims/__init__.py
media_processing_lib/video/libs/pims/reader.py
media_processing_lib/video/mpl_video/__init__.py
media_processing_lib/video/mpl_video/mpl_video.py
media_processing_lib/video/utils/__init__.py
media_processing_lib/video/utils/intrinsics.py
media_processing_lib-0.3.dist-info/LICENSE.TXT
media_processing_lib-0.3.dist-info/METADATA
media_processing_lib-0.3.dist-info/WHEEL
media_processing_lib-0.3.dist-info/top_level.txt
media_processing_lib-0.3.dist-info/RECORD
